fake_proxy/__init__.py
fake_proxy/core/__init__.py
fake_proxy/core/api.py
fake_proxy/core/exceptions.py
fake_proxy/core/proxysource.py
fake_proxy/core/proxysourcemanager.py
fake_proxy/sources/__init__.py
fake_proxy/sources/freeproxylist.py
fake_proxy/sources/socks-proxy.py
fake_proxy/sources/sslproxies.py
test/sample_proxysources/__init__.py
test/sample_proxysources/sample_proxy_list.py
fake_proxy-0.1.1.dist-info/LICENSE
fake_proxy-0.1.1.dist-info/METADATA
fake_proxy-0.1.1.dist-info/WHEEL
fake_proxy-0.1.1.dist-info/top_level.txt
fake_proxy-0.1.1.dist-info/RECORD
