Metadata-Version: 2.1
Name: fake-proxy
Version: 0.1.1
Summary: Library that finds public proxies
Home-page: https://github.com/machinia/fake-proxy
Author: Pablo Ahumada, Jorge Capona
Author-email: pablo.ahumadadiaz@gmail.com, jcapona@gmail.com
License: MIT
Keywords: proxy proxies rotate scrape
Platform: UNKNOWN
Classifier: Development Status :: 3 - Alpha
Classifier: Intended Audience :: Developers
Classifier: Topic :: Software Development
Classifier: Topic :: System
Classifier: License :: OSI Approved :: MIT License
Classifier: Programming Language :: Python :: 3.6
Requires-Dist: beautifulsoup4 (<5,>=4.8)
Requires-Dist: requests (<3,>=2.22)
